tsalib/__init__.py
tsalib/backend.py
tsalib/tensor_ops.py
tsalib/transforms.py
tsalib/ts.py
tsalib/ts_lite.py
tsalib/tsn.py
tsalib/utils.py
tsalib-0.2.2.dist-info/LICENSE
tsalib-0.2.2.dist-info/METADATA
tsalib-0.2.2.dist-info/WHEEL
tsalib-0.2.2.dist-info/top_level.txt
tsalib-0.2.2.dist-info/RECORD
