Metadata-Version: 2.1
Name: tsalib
Version: 0.2.2
Summary: TSAlib: Support for Named Tensor Shapes
Home-page: https://github.com/ofnote/tsalib
Author: Nishant Sinha
Author-email: nishantsinha@acm.org
License: Apache 2.0
Platform: POSIX
Classifier: Environment :: Console
Classifier: Intended Audience :: Developers
Classifier: License :: OSI Approved :: Apache Software License
Classifier: Operating System :: OS Independent
Classifier: Programming Language :: Python :: 3.6
Classifier: Programming Language :: Python :: 3.7
Classifier: Topic :: Software Development
Classifier: Topic :: Scientific/Engineering :: Artificial Intelligence
Requires-Dist: sympy
